setup.py
haiderbhai_distributions/Binomialdistribution.py
haiderbhai_distributions/Gaussiandistribution.py
haiderbhai_distributions/Generaldistribution.py
haiderbhai_distributions/__init__.py
haiderbhai_distributions.egg-info/PKG-INFO
haiderbhai_distributions.egg-info/SOURCES.txt
haiderbhai_distributions.egg-info/dependency_links.txt
haiderbhai_distributions.egg-info/not-zip-safe
haiderbhai_distributions.egg-info/top_level.txt