Metadata-Version: 1.0
Name: haiderbhai-distributions
Version: 10.0
Summary: Binomial and Gaussian distributions
Home-page: UNKNOWN
Author: Syed Haider Ali Shah
Author-email: 22110282@lums.edu.pk
License: UNKNOWN
Platform: UNKNOWN
